mpy_cross_v6_2-1.1.1.data/platlib/mpy_cross_v6_2/__init__.py
mpy_cross_v6_2-1.1.1.data/platlib/mpy_cross_v6_2/__main__.py
mpy_cross_v6_2-1.1.1.data/platlib/mpy_cross_v6_2/mpy-cross
mpy_cross_v6_2-1.1.1.data/platlib/mpy_cross_v6_2/py.typed
mpy_cross_v6_2-1.1.1.dist-info/METADATA
mpy_cross_v6_2-1.1.1.dist-info/WHEEL
mpy_cross_v6_2-1.1.1.dist-info/entry_points.txt
mpy_cross_v6_2-1.1.1.dist-info/top_level.txt
mpy_cross_v6_2-1.1.1.dist-info/RECORD
