Metadata-Version: 2.4
Name: mpy-cross-v6.2
Version: 1.1.1
Summary: Python wrapper for the mpy-cross tool from MicroPython.
